{
  "formatVersion": 1,
  "database": {
    "version": 5,
    "identityHash": "016ea01e9724945ff094027cac3b0b4c",
    "entities": [
      {
        "tableName": "medications",
        "createSql": "CREATE TABLE IF NOT EXISTS `${TABLE_NAME}` (`id` INTEGER PRIMARY KEY AUTOINCREMENT NOT NULL, `name` TEXT NOT NULL, `dosageInstruction` TEXT NOT NULL, `doseAmount` REAL NOT NULL, `doseUnit` TEXT NOT NULL, `treatmentType` TEXT NOT NULL, `startDate` TEXT NOT NULL, `endDate` TEXT, `currentStock` REAL NOT NULL, `totalRequiredStock` REAL, `foodRelation` TEXT NOT NULL, `lowStockThresholdDays` REAL NOT NULL, `isActive` INTEGER NOT NULL, `createdAt` TEXT NOT NULL, `updatedAt` TEXT NOT NULL)",
        "fields": [
          {
            "fieldPath": "id",
            "columnName": "id",
            "affinity": "INTEGER",
            "notNull": true
          },
          {
            "fieldPath": "name",
            "columnName": "name",
            "affinity": "TEXT",
            "notNull": true
          },
          {
            "fieldPath": "dosageInstruction",
            "columnName": "dosageInstruction",
            "affinity": "TEXT",
            "notNull": true
          },
          {
            "fieldPath": "doseAmount",
            "columnName": "doseAmount",
            "affinity": "REAL",
            "notNull": true
          },
          {
            "fieldPath": "doseUnit",
            "columnName": "doseUnit",
            "affinity": "TEXT",
            "notNull": true
          },
          {
            "fieldPath": "treatmentType",
            "columnName": "treatmentType",
            "affinity": "TEXT",
            "notNull": true
          },
          {
            "fieldPath": "startDate",
            "columnName": "startDate",
            "affinity": "TEXT",
            "notNull": true
          },
          {
            "fieldPath": "endDate",
            "columnName": "endDate",
            "affinity": "TEXT",
            "notNull": false
          },
          {
            "fieldPath": "currentStock",
            "columnName": "currentStock",
            "affinity": "REAL",
            "notNull": true
          },
          {
            "fieldPath": "totalRequiredStock",
            "columnName": "totalRequiredStock",
            "affinity": "REAL",
            "notNull": false
          },
          {
            "fieldPath": "foodRelation",
            "columnName": "foodRelation",
            "affinity": "TEXT",
            "notNull": true
          },
          {
            "fieldPath": "lowStockThresholdDays",
            "columnName": "lowStockThresholdDays",
            "affinity": "REAL",
            "notNull": true
          },
          {
            "fieldPath": "isActive",
            "columnName": "isActive",
            "affinity": "INTEGER",
            "notNull": true
          },
          {
            "fieldPath": "createdAt",
            "columnName": "createdAt",
            "affinity": "TEXT",
            "notNull": true
          },
          {
            "fieldPath": "updatedAt",
            "columnName": "updatedAt",
            "affinity": "TEXT",
            "notNull": true
          }
        ],
        "primaryKey": {
          "autoGenerate": true,
          "columnNames": [
            "id"
          ]
        },
        "indices": [],
        "foreignKeys": []
      },
      {
        "tableName": "medication_schedules",
        "createSql": "CREATE TABLE IF NOT EXISTS `${TABLE_NAME}` (`id` INTEGER PRIMARY KEY AUTOINCREMENT NOT NULL, `medicationId` INTEGER NOT NULL, `scheduleType` TEXT NOT NULL, `timeOfDay` TEXT, `doseAmount` REAL, `intervalValue` INTEGER, `intervalUnit` TEXT, `daysOfWeek` TEXT, `dayOfMonth` INTEGER, `isActive` INTEGER NOT NULL, FOREIGN KEY(`medicationId`) REFERENCES `medications`(`id`) ON UPDATE NO ACTION ON DELETE CASCADE )",
        "fields": [
          {
            "fieldPath": "id",
            "columnName": "id",
            "affinity": "INTEGER",
            "notNull": true
          },
          {
            "fieldPath": "medicationId",
            "columnName": "medicationId",
            "affinity": "INTEGER",
            "notNull": true
          },
          {
            "fieldPath": "scheduleType",
            "columnName": "scheduleType",
            "affinity": "TEXT",
            "notNull": true
          },
          {
            "fieldPath": "timeOfDay",
            "columnName": "timeOfDay",
            "affinity": "TEXT",
            "notNull": false
          },
          {
            "fieldPath": "doseAmount",
            "columnName": "doseAmount",
            "affinity": "REAL",
            "notNull": false
          },
          {
            "fieldPath": "intervalValue",
            "columnName": "intervalValue",
            "affinity": "INTEGER",
            "notNull": false
          },
          {
            "fieldPath": "intervalUnit",
            "columnName": "intervalUnit",
            "affinity": "TEXT",
            "notNull": false
          },
          {
            "fieldPath": "daysOfWeek",
            "columnName": "daysOfWeek",
            "affinity": "TEXT",
            "notNull": false
          },
          {
            "fieldPath": "dayOfMonth",
            "columnName": "dayOfMonth",
            "affinity": "INTEGER",
            "notNull": false
          },
          {
            "fieldPath": "isActive",
            "columnName": "isActive",
            "affinity": "INTEGER",
            "notNull": true
          }
        ],
        "primaryKey": {
          "autoGenerate": true,
          "columnNames": [
            "id"
          ]
        },
        "indices": [
          {
            "name": "index_medication_schedules_medicationId",
            "unique": false,
            "columnNames": [
              "medicationId"
            ],
            "orders": [],
            "createSql": "CREATE INDEX IF NOT EXISTS `index_medication_schedules_medicationId` ON `${TABLE_NAME}` (`medicationId`)"
          }
        ],
        "foreignKeys": [
          {
            "table": "medications",
            "onDelete": "CASCADE",
            "onUpdate": "NO ACTION",
            "columns": [
              "medicationId"
            ],
            "referencedColumns": [
              "id"
            ]
          }
        ]
      },
      {
        "tableName": "dose_events",
        "createSql": "CREATE TABLE IF NOT EXISTS `${TABLE_NAME}` (`id` INTEGER PRIMARY KEY AUTOINCREMENT NOT NULL, `medicationId` INTEGER NOT NULL, `scheduledDateTime` TEXT NOT NULL, `status` TEXT NOT NULL, `takenDateTime` TEXT, `skippedDateTime` TEXT, `doseAmount` REAL NOT NULL, `deductedAmount` REAL, `note` TEXT, FOREIGN KEY(`medicationId`) REFERENCES `medications`(`id`) ON UPDATE NO ACTION ON DELETE CASCADE )",
        "fields": [
          {
            "fieldPath": "id",
            "columnName": "id",
            "affinity": "INTEGER",
            "notNull": true
          },
          {
            "fieldPath": "medicationId",
            "columnName": "medicationId",
            "affinity": "INTEGER",
            "notNull": true
          },
          {
            "fieldPath": "scheduledDateTime",
            "columnName": "scheduledDateTime",
            "affinity": "TEXT",
            "notNull": true
          },
          {
            "fieldPath": "status",
            "columnName": "status",
            "affinity": "TEXT",
            "notNull": true
          },
          {
            "fieldPath": "takenDateTime",
            "columnName": "takenDateTime",
            "affinity": "TEXT",
            "notNull": false
          },
          {
            "fieldPath": "skippedDateTime",
            "columnName": "skippedDateTime",
            "affinity": "TEXT",
            "notNull": false
          },
          {
            "fieldPath": "doseAmount",
            "columnName": "doseAmount",
            "affinity": "REAL",
            "notNull": true
          },
          {
            "fieldPath": "deductedAmount",
            "columnName": "deductedAmount",
            "affinity": "REAL",
            "notNull": false
          },
          {
            "fieldPath": "note",
            "columnName": "note",
            "affinity": "TEXT",
            "notNull": false
          }
        ],
        "primaryKey": {
          "autoGenerate": true,
          "columnNames": [
            "id"
          ]
        },
        "indices": [
          {
            "name": "index_dose_events_medicationId",
            "unique": false,
            "columnNames": [
              "medicationId"
            ],
            "orders": [],
            "createSql": "CREATE INDEX IF NOT EXISTS `index_dose_events_medicationId` ON `${TABLE_NAME}` (`medicationId`)"
          },
          {
            "name": "index_dose_events_medicationId_scheduledDateTime",
            "unique": true,
            "columnNames": [
              "medicationId",
              "scheduledDateTime"
            ],
            "orders": [],
            "createSql": "CREATE UNIQUE INDEX IF NOT EXISTS `index_dose_events_medicationId_scheduledDateTime` ON `${TABLE_NAME}` (`medicationId`, `scheduledDateTime`)"
          }
        ],
        "foreignKeys": [
          {
            "table": "medications",
            "onDelete": "CASCADE",
            "onUpdate": "NO ACTION",
            "columns": [
              "medicationId"
            ],
            "referencedColumns": [
              "id"
            ]
          }
        ]
      },
      {
        "tableName": "vaccinations",
        "createSql": "CREATE TABLE IF NOT EXISTS `${TABLE_NAME}` (`id` INTEGER PRIMARY KEY AUTOINCREMENT NOT NULL, `name` TEXT NOT NULL, `doseLabel` TEXT NOT NULL, `scheduledDateTime` TEXT NOT NULL, `status` TEXT NOT NULL, `completedDateTime` TEXT, `note` TEXT, `createdAt` TEXT NOT NULL, `updatedAt` TEXT NOT NULL)",
        "fields": [
          {
            "fieldPath": "id",
            "columnName": "id",
            "affinity": "INTEGER",
            "notNull": true
          },
          {
            "fieldPath": "name",
            "columnName": "name",
            "affinity": "TEXT",
            "notNull": true
          },
          {
            "fieldPath": "doseLabel",
            "columnName": "doseLabel",
            "affinity": "TEXT",
            "notNull": true
          },
          {
            "fieldPath": "scheduledDateTime",
            "columnName": "scheduledDateTime",
            "affinity": "TEXT",
            "notNull": true
          },
          {
            "fieldPath": "status",
            "columnName": "status",
            "affinity": "TEXT",
            "notNull": true
          },
          {
            "fieldPath": "completedDateTime",
            "columnName": "completedDateTime",
            "affinity": "TEXT",
            "notNull": false
          },
          {
            "fieldPath": "note",
            "columnName": "note",
            "affinity": "TEXT",
            "notNull": false
          },
          {
            "fieldPath": "createdAt",
            "columnName": "createdAt",
            "affinity": "TEXT",
            "notNull": true
          },
          {
            "fieldPath": "updatedAt",
            "columnName": "updatedAt",
            "affinity": "TEXT",
            "notNull": true
          }
        ],
        "primaryKey": {
          "autoGenerate": true,
          "columnNames": [
            "id"
          ]
        },
        "indices": [],
        "foreignKeys": []
      }
    ],
    "views": [],
    "setupQueries": [
      "CREATE TABLE IF NOT EXISTS room_master_table (id INTEGER PRIMARY KEY,identity_hash TEXT)",
      "INSERT OR REPLACE INTO room_master_table (id,identity_hash) VALUES(42, '016ea01e9724945ff094027cac3b0b4c')"
    ]
  }
}